<?xml version="1.0"?>
<Config>
  <TagsToIgnore>8,9,10,34,52,370,49,56,115,128</TagsToIgnore>
  <QFNSessionSettings>
    <Default>
      <FileStorePath>store</FileStorePath>
      <FileLogPath>log</FileLogPath>
      <ConnectionType>initiator</ConnectionType>
      <ReconnectInterval>60</ReconnectInterval>
      <BeginString>FIX.4.2</BeginString>
      <SenderCompID>LSECONF</SenderCompID>
      <TargetCompID>LSEHub</TargetCompID>
      <StartTime>22:30:00</StartTime>
      <EndTime>22:29:59</EndTime>
      <HeartBtInt>30</HeartBtInt>
      <SocketConnectPort>2001</SocketConnectPort>
      <SocketConnectHost>127.0.0.1</SocketConnectHost>
      <DataDictionary>FIX42.xml</DataDictionary>
      <ResetOnLogon>Y</ResetOnLogon>
    </Default>
    <Session>
      <BeginString>FIX.4.2</BeginString>
      <SenderCompID>LSECONF</SenderCompID>
      <TargetCompID>LSEHub</TargetCompID>
      <StartTime>22:30:00</StartTime>
      <EndTime>22:29:59</EndTime>
      <HeartBtInt>30</HeartBtInt>
      <SocketConnectPort>2001</SocketConnectPort>
      <SocketConnectHost>127.0.0.1</SocketConnectHost>
      <DataDictionary>FIX42.xml</DataDictionary>
      <ResetOnLogon>Y</ResetOnLogon>
    </Session>
  </QFNSessionSettings>
  <Scenarios>
	  <Scenario Name="BLK_SC1_BUY" Type="Explicit" IgnoreSessionMessages="true" IgnoreUnexpectedMessages="true" SenderCompID="LSECONF" TargetCompID="LSEHub" DeliverToCompID="INI002">
		  <TX></TX>
		  <RX CheckType="Wait"></RX>
		  <RX CheckType="Expect"></RX>
		  <RX CheckType="Ignore"></RX>
	  </Scenario>
    <Scenario Name="BLK_SC2_BUY" Type="Raw" Side="Buy" IgnoreSessionMessages="true" IgnoreUnexpectedMessages="true" SenderCompID="LSECONF" TargetCompID="LSEHub" DeliverToCompID="INI002">
      <Message>8=FIX.4.2|9=198|35=D|49=LSEHub|56=ROYB|115=BLKUKNITE|128=NITE|34=2031|116=AH|52=20140822-14:40:37|370=20140822-14:40:37|11=yAA0004-20140822|21=3|100=L|55=BH4HKS3|48=BH4HKS3|22=2|54=1|60=20140822-14:40:37|38=144|40=1|15=GBp|10=179|</Message>
      <Message>8=FIX.4.2|9=244|35=8|49=NITE|56=LSEHub|34=2016|52=20140822-14:41:56|128=BLKUKNITE|129=AH|32=0|31=0.0000|151=144|14=0|6=0.0000|60=20140822-14:41:56|11=yAA0004-20140822|55=BH4HKS3|54=1|38=144|40=1|17=657808632|22=2|48=BH4HKS3|15=GBp|20=0|39=0|150=0|37=657808633|10=157|</Message>
      <Message>8=FIX.4.2|9=267|35=8|49=NITE|56=LSEHub|34=2025|52=20140822-14:43:56|128=BLKUKNITE|129=AH|32=44|31=204.7000|151=100|14=44|6=204.7000|60=20140822-14:43:56|11=yAA0004-20140822|55=BH4HKS3|54=1|38=144|40=1|17=657808643|22=2|48=BH4HKS3|15=GBp|20=0|150=1|39=1|75=20140822|29=4|37=657808633|10=006|</Message>
      <Message>8=FIX.4.2|9=234|35=G|49=LSEHub|56=NITE|115=BLKUKNITE|34=2042|116=AH|52=20140822-14:44:08|370=20140822-14:44:08|41=yAA0004-20140822|11=yAA0008-20140822|21=3|100=L|55=BH4HKS3|48=BH4HKS3|22=2|54=1|60=20140822-14:44:08|38=144|40=2|44=205.58200000|15=GBp|10=214|</Message>
      <Message>8=FIX.4.2|9=298|35=8|49=NITE|56=LSEHub|34=2037|52=20140822-14:49:31|128=BLKUKNITE|129=AH|32=0|31=0.0000|151=100|14=44|6=204.7000|60=20140822-14:49:31|11=yAA0008-20140822|55=BH4HKS3|54=1|38=144|40=2|44=205.5820|17=657808644|22=2|48=BH4HKS3|15=GBp|20=0|39=E|150=E|58=Pending Replace|41=yAA0004-20140822|37=657808633|10=034|</Message>
      <Message>8=FIX.4.2|9=295|35=8|49=NITE|56=LSEHub|34=2038|52=20140822-14:49:40|128=BLKUKNITE|129=AH|32=0|31=0.0000|151=100|14=44|6=204.7000|60=20140822-14:49:40|11=yAA0008-20140822|55=BH4HKS3|54=1|38=144|40=2|44=205.58200000|17=657808645|22=2|48=BH4HKS3|15=GBp|20=0|150=5|41=yAA0004-20140822|58=REPLACED|37=657808633|39=1|10=092|</Message>
      <Message>8=FIX.4.2|9=276|35=8|49=NITE|56=LSEHub|34=2040|52=20140822-14:50:11|128=BLKUKNITE|129=AH|32=40|31=205.0000|151=60|14=84|6=204.8429|60=20140822-14:50:11|11=yAA0008-20140822|55=BH4HKS3|54=1|38=144|40=2|44=2.0500|17=657808647|22=2|48=BH4HKS3|15=GBp|20=0|150=1|39=1|75=20140822|29=4|37=657808633|10=160|</Message>
      <Message>8=FIX.4.2|9=234|35=G|49=LSEHub|56=NITE|115=BLKUKNITE|34=2056|116=AH|52=20140822-14:50:26|370=20140822-14:50:26|41=yAA0008-20140822|11=yAA0009-20140822|21=3|100=L|55=BH4HKS3|48=BH4HKS3|22=2|54=1|60=20140822-14:50:26|38=144|40=2|44=205.70000000|15=GBp|10=207|</Message>
      <Message>8=FIX.4.2|9=297|35=8|49=NITE|56=LSEHub|34=2041|52=20140822-14:50:26|128=BLKUKNITE|129=AH|32=0|31=0.0000|151=60|14=84|6=204.8429|60=20140822-14:50:26|11=yAA0009-20140822|55=BH4HKS3|54=1|38=144|40=2|44=205.7000|17=657808648|22=2|48=BH4HKS3|15=GBp|20=0|39=E|150=E|58=Pending Replace|41=yAA0008-20140822|37=657808633|10=254|</Message>
      <Message>8=FIX.4.2|9=294|35=8|49=NITE|56=LSEHub|34=2042|52=20140822-14:50:32|128=BLKUKNITE|129=AH|32=0|31=0.0000|151=60|14=84|6=204.8429|60=20140822-14:50:32|11=yAA0009-20140822|55=BH4HKS3|54=1|38=144|40=2|44=205.70000000|17=657808649|22=2|48=BH4HKS3|15=GBp|20=0|150=5|41=yAA0008-20140822|58=REPLACED|37=657808633|39=1|10=050|</Message>
      <Message>8=FIX.4.2|9=299|35=8|49=NITE|56=LSEHub|34=2043|52=20140822-14:50:48|128=BLKUKNITE|129=AH|32=0|31=0.0000|151=0|14=84|6=204.8429|60=20140822-14:50:48|11=yAA0009-20140822|55=BH4HKS3|54=1|38=144|40=2|44=205.7000|17=657808650|22=2|48=BH4HKS3|15=GBp|41=yAA0009-20140822|20=0|39=4|150=4|58=CANCELED BY TRADER|37=657808633|10=215|</Message>
    </Scenario>
  </Scenarios>
</Config>













